ufo_model_loader/__init__.py
ufo_model_loader/__main__.py
ufo_model_loader/cli.py
ufo_model_loader/commands.py
ufo_model_loader/common.py
ufo_model_loader/model.py
ufo_model_loader/param_card.py
ufo_model_loader/symbolica_processing.py
ufo_model_loader/data/models/scalars/__init__.py
ufo_model_loader/data/models/scalars/coupling_orders.py
ufo_model_loader/data/models/scalars/couplings.py
ufo_model_loader/data/models/scalars/function_library.py
ufo_model_loader/data/models/scalars/lorentz.py
ufo_model_loader/data/models/scalars/object_library.py
ufo_model_loader/data/models/scalars/parameters.py
ufo_model_loader/data/models/scalars/particles.py
ufo_model_loader/data/models/scalars/restrict_default.dat
ufo_model_loader/data/models/scalars/restrict_full.dat
ufo_model_loader/data/models/scalars/run_write_param_card.py
ufo_model_loader/data/models/scalars/vertices.py
ufo_model_loader/data/models/scalars/write_param_card.py
ufo_model_loader/data/models/scalars/__pycache__/__init__.cpython-312.pyc
ufo_model_loader/data/models/scalars/__pycache__/coupling_orders.cpython-312.pyc
ufo_model_loader/data/models/scalars/__pycache__/couplings.cpython-312.pyc
ufo_model_loader/data/models/scalars/__pycache__/function_library.cpython-312.pyc
ufo_model_loader/data/models/scalars/__pycache__/lorentz.cpython-312.pyc
ufo_model_loader/data/models/scalars/__pycache__/object_library.cpython-312.pyc
ufo_model_loader/data/models/scalars/__pycache__/parameters.cpython-312.pyc
ufo_model_loader/data/models/scalars/__pycache__/particles.cpython-312.pyc
ufo_model_loader/data/models/scalars/__pycache__/vertices.cpython-312.pyc
ufo_model_loader/data/models/sm/__init__.py
ufo_model_loader/data/models/sm/build_restrict.py
ufo_model_loader/data/models/sm/coupling_orders.py
ufo_model_loader/data/models/sm/couplings.py
ufo_model_loader/data/models/sm/decays.py
ufo_model_loader/data/models/sm/function_library.py
ufo_model_loader/data/models/sm/lorentz.py
ufo_model_loader/data/models/sm/object_library.py
ufo_model_loader-0.1.4.dist-info/licenses/LICENSE
ufo_model_loader-0.1.4.dist-info/METADATA
ufo_model_loader-0.1.4.dist-info/WHEEL
ufo_model_loader-0.1.4.dist-info/entry_points.txt
ufo_model_loader-0.1.4.dist-info/top_level.txt
ufo_model_loader-0.1.4.dist-info/RECORD
