Metadata-Version: 2.4
Name: ufo_model_loader
Version: 0.1.4
Summary: Tool for loading high-energy physics models in the UFO format and export them in flat JSON format.
Author-email: Valentin Hirschi <valentin.hirschi@gmail.com>
License: The MIT License (MIT)
Project-URL: Homepage, https://github.com/alphal00p/ufo_model_loader
Project-URL: Issues, https://github.com/alphal00p/ufo_model_loader/issues
Classifier: Programming Language :: Python :: 3.11
Classifier: Operating System :: OS Independent
Requires-Python: >=3.11
License-File: LICENSE
Requires-Dist: symbolica>=0.18.0
Provides-Extra: prettyjson
Requires-Dist: jsbeautifier; extra == "prettyjson"
Requires-Dist: pytest; extra == "prettyjson"
Dynamic: license-file
